ctgu_list_tables_tool/__init__.py
ctgu_list_tables_tool/db_utils.py
ctgu_list_tables_tool/log_util.py
ctgu_list_tables_tool/postgre_utils.py
ctgu_list_tables_tool-0.1.0.dist-info/WHEEL
ctgu_list_tables_tool-0.1.0.dist-info/entry_points.txt
ctgu_list_tables_tool-0.1.0.dist-info/METADATA
ctgu_list_tables_tool-0.1.0.dist-info/RECORD
